ruffianTest/__init__.py
ruffianTest/common/__init__.py
ruffianTest/common/data/GenerateTheData.py
ruffianTest/common/data/__init__.py
ruffianTest/common/db/__init__.py
ruffianTest/common/db/mysql.py
ruffianTest/common/document/__init__.py
ruffianTest/common/document/operation_csv.py
ruffianTest/common/document/operation_excel.py
ruffianTest/common/encryption/__init__.py
ruffianTest/common/encryption/encryption.py
ruffianTest/common/mail/__init__.py
ruffianTest/common/mail/mail.py
ruffianTest/common/picture/__init__.py
ruffianTest/common/picture/picture_synthesis.py
ruffianTest/common/picture/picture_to_base64.py
ruffianTest/common/server/__init__.py
ruffianTest/common/server/server_client.py
ruffianTest-0.0.2.dist-info/LICENSE
ruffianTest-0.0.2.dist-info/METADATA
ruffianTest-0.0.2.dist-info/WHEEL
ruffianTest-0.0.2.dist-info/top_level.txt
ruffianTest-0.0.2.dist-info/RECORD
