Metadata-Version: 2.1
Name: ruffianTest
Version: 0.0.2
Summary: test
Home-page: https://github.com/the-ruffian/ruffian_test
Download-URL: https://github.com/the-ruffian/ruffian_test
Author: The-Ruffian
Author-email: 
License: MIT License
Keywords: bug_pz,the-ruffian,ruffianTest,ruffian,test
Platform: all
Classifier: Intended Audience :: Developers
Classifier: Operating System :: OS Independent
Classifier: Natural Language :: Chinese (Simplified)
Classifier: Programming Language :: Python :: 3
Classifier: Topic :: Software Development :: Testing
Classifier: Development Status :: 5 - Production/Stable
License-File: LICENSE
Requires-Dist: PyMySQL
Requires-Dist: xlrd
Requires-Dist: xlwt
